Base/__init__.py
Base/builder.py
Wordbuilds-0.0.3.dist-info/METADATA
Wordbuilds-0.0.3.dist-info/WHEEL
Wordbuilds-0.0.3.dist-info/top_level.txt
Wordbuilds-0.0.3.dist-info/RECORD
